LICENSE
README.md
pyproject.toml
trpc/__init__.py
trpc/procedure.py
trpc/py.typed
trpc/router.py
trpc/server.py
trpc_core-0.1.0.dist-info/METADATA
trpc_core-0.1.0.dist-info/WHEEL
trpc_core-0.1.0.dist-info/licenses/LICENSE
trpc_core-0.1.0.dist-info/RECORD
